README.txt
setup.py
easyzone/__init__.py
easyzone/easyzone.py
easyzone/zone_check.py
easyzone/zone_reload.py
easyzone3.egg-info/PKG-INFO
easyzone3.egg-info/SOURCES.txt
easyzone3.egg-info/dependency_links.txt
easyzone3.egg-info/requires.txt
easyzone3.egg-info/top_level.txt