Metadata-Version: 1.1
Name: easyzone3
Version: 1.2.3
Summary: Easy Zone - DNS Zone abstraction module
Home-page: https://github.com/trdcaz/easyzone3/
Author: trdcaz
Author-email: trdcaz@gmail.com
License: MIT
Platform: UNKNOWN
Classifier: Development Status :: 5 - Production/Stable
Classifier: License :: OSI Approved :: MIT License
Classifier: Topic :: Internet :: Name Service (DNS)
Classifier: Topic :: System :: Systems Administration
